fdamages
